hexlet/points/__init__.py
hexlet_points-0.3.0.dist-info/LICENSE
hexlet_points-0.3.0.dist-info/WHEEL
hexlet_points-0.3.0.dist-info/METADATA
hexlet_points-0.3.0.dist-info/RECORD
